algebratrio/__init__.py
algebratrio/archivoTest.py
algebratrio/mi_modulo.py
algebratrio-0.0.1.dist-info/METADATA
algebratrio-0.0.1.dist-info/WHEEL
algebratrio-0.0.1.dist-info/RECORD
